setup.cfg
setup.py
his2h5/__init__.py
his2h5/fftfuncs.py
his2h5/mandel.py
his2h5/mockNDarray.py
his2h5/readerHIS.py
his2h5/tool.py
his2h5.egg-info/PKG-INFO
his2h5.egg-info/SOURCES.txt
his2h5.egg-info/dependency_links.txt
his2h5.egg-info/entry_points.txt
his2h5.egg-info/not-zip-safe
his2h5.egg-info/requires.txt
his2h5.egg-info/top_level.txt