Metadata-Version: 1.0
Name: his2h5
Version: 0.1dev
Summary: Command line utility to convert beterrn Hamamatsu Image Sequence (.HIS) files and HDF5 files.
Home-page: UNKNOWN
Author: Rich Wareham
Author-email: rjw57@cam.ac.uk
License: BSD
Platform: UNKNOWN
